debby_root/__init__.py
debby_root/cli.py
debby_root-0.1.0.dist-info/licenses/LICENSE
debby_root-0.1.0.dist-info/METADATA
debby_root-0.1.0.dist-info/WHEEL
debby_root-0.1.0.dist-info/entry_points.txt
debby_root-0.1.0.dist-info/top_level.txt
debby_root-0.1.0.dist-info/RECORD
