Metadata-Version: 2.4
Name: debby_root
Version: 0.1.0
Summary: Ein CLI-Wrapper für debootstrap
Author-email: Calvin Ronksley <hexzhen3x7@blackzspace.de>
License: MIT
Requires-Python: >=3.7
License-File: LICENSE
Dynamic: license-file
